auth_code_flow/__init__.py
auth_code_flow/adapters.py
auth_code_flow/exceptions.py
auth_code_flow/managers.py
LICENSE
auth_code_flow-0.2.1.dist-info/LICENSE
auth_code_flow-0.2.1.dist-info/WHEEL
auth_code_flow-0.2.1.dist-info/METADATA
auth_code_flow-0.2.1.dist-info/RECORD
