Metadata-Version: 2.1
Name: auth-code-flow
Version: 0.2.1
Summary: Auth Code Flow (`auth-code-flow`) is a utility for obtaining access tokens on behalf of resource owners using the OAuth 2.0 authentication code flow
Home-page: https://gitlab.com/a-thousand-juniors/auth-code-flow
License: MIT
Keywords: oauth,authorization grant,authorization code,authorization code flow
Author: Mfon Eti-mfon
Author-email: mfonetimfon@gmail.com
Requires-Python: >=3.8,<4.0
Classifier: Environment :: Web Environment
Classifier: License :: OSI Approved :: MIT License
Classifier: Operating System :: OS Independent
Classifier: Programming Language :: Python
Classifier: Programming Language :: Python :: 3
Classifier: Programming Language :: Python :: 3.8
Classifier: Programming Language :: Python :: 3.9
Requires-Dist: requests (>=2.25.1,<3.0.0)
Requires-Dist: urllib3 (>=1.26.4,<2.0.0)
Project-URL: Repository, https://gitlab.com/a-thousand-juniors/auth-code-flow
